igeWebview.cp39-win_amd64.pyd
igeWebview-0.1.0.dist-info/LICENSE
igeWebview-0.1.0.dist-info/METADATA
igeWebview-0.1.0.dist-info/WHEEL
igeWebview-0.1.0.dist-info/top_level.txt
igeWebview-0.1.0.dist-info/RECORD
